<?xml version='1.0' encoding='UTF-8'?>
<!DOCTYPE markables SYSTEM "markables.dtd">
<markables xmlns="www.eml.org/NameSpaces/target">
<markable anaphref="empty" diff_type="missing" id="markable_1005007" mmax_level="target" preferred="true" sentiment_ref="empty" span="word_52..word_60" /><markable anaphref="empty" diff_type="missing" id="markable_100500121" mmax_level="target" preferred="true" sentiment_ref="empty" span="word_64..word_66" /><markable anaphref="empty" diff_type="missing" id="markable_10050012" mmax_level="target" preferred="true" sentiment_ref="empty" span="word_105,word_107..word_109" /><markable anaphref="markable_100500126" diff_type="missing" id="markable_100500124" mmax_level="target" preferred="true" sentiment_ref="empty" span="word_124" /><markable anaphref="empty" diff_type="missing" id="markable_10050020" mmax_level="target" preferred="true" sentiment_ref="empty" span="word_150..word_153" /><markable anaphref="empty" diff_type="missing" id="markable_10050023" mmax_level="target" preferred="true" sentiment_ref="empty" span="word_180..word_181" /><markable anaphref="empty" diff_type="missing" id="markable_10050030" mmax_level="target" preferred="true" sentiment_ref="empty" span="word_215..word_220" /><markable anaphref="empty" diff_type="missing" id="markable_10050041" mmax_level="target" preferred="true" sentiment_ref="empty" span="word_353..word_355" /><markable anaphref="empty" diff_type="missing" id="markable_10050045" mmax_level="target" preferred="true" sentiment_ref="empty" span="word_405..word_409" /><markable anaphref="empty" diff_type="missing" id="markable_100500135" mmax_level="target" preferred="true" sentiment_ref="empty" span="word_463" /><markable anaphref="empty" diff_type="missing" id="markable_100500138" mmax_level="target" preferred="true" sentiment_ref="empty" span="word_512..word_519" /><markable anaphref="empty" diff_type="missing" id="markable_100500140" mmax_level="target" preferred="true" sentiment_ref="empty" span="word_534" /><markable anaphref="empty" diff_type="missing" id="markable_10050059" mmax_level="target" preferred="true" sentiment_ref="empty" span="word_545..word_552,word_555" /><markable anaphref="empty" diff_type="missing" id="markable_100500143" mmax_level="target" preferred="true" sentiment_ref="empty" span="word_600..word_604,word_608" /><markable anaphref="empty" diff_type="missing" id="markable_10050074" mmax_level="target" preferred="true" sentiment_ref="empty" span="word_650,word_658..word_661" /><markable anaphref="empty" diff_type="missing" id="markable_10050080" mmax_level="target" preferred="true" sentiment_ref="empty" span="word_673..word_680" /><markable anaphref="empty" diff_type="missing" id="markable_10050082" mmax_level="target" preferred="true" sentiment_ref="empty" span="word_690" /><markable anaphref="empty" diff_type="missing" id="markable_10050085" mmax_level="target" preferred="true" sentiment_ref="empty" span="word_745" /><markable anaphref="empty" diff_type="missing" id="markable_10050089" mmax_level="target" preferred="true" sentiment_ref="empty" span="word_795..word_808" /><markable anaphref="empty" diff_type="missing" id="markable_10050094" mmax_level="target" preferred="true" sentiment_ref="empty" span="word_896..word_897,word_899..word_900" /><markable anaphref="empty" diff_type="missing" id="markable_100500150" mmax_level="target" preferred="true" sentiment_ref="empty" span="word_932..word_934" /><markable anaphref="empty" diff_type="missing" id="markable_100500163" mmax_level="target" preferred="true" sentiment_ref="empty" span="word_1166..word_1173" /><markable anaphref="empty" diff_type="missing" id="markable_100500165" mmax_level="target" preferred="true" sentiment_ref="empty" span="word_1176" /><markable anaphref="empty" diff_type="missing" id="markable_100500104" mmax_level="target" preferred="true" sentiment_ref="empty" span="word_1199,word_1201..word_1203" /><markable anaphref="empty" diff_type="missing" id="markable_100500168" mmax_level="target" preferred="true" sentiment_ref="empty" span="word_1210..word_1213" /><markable anaphref="empty" diff_type="missing" id="markable_100500171" mmax_level="target" preferred="true" sentiment_ref="empty" span="word_1234" /><markable anaphref="empty" diff_type="missing" id="markable_100500174" mmax_level="target" preferred="true" sentiment_ref="empty" span="word_1513" /><markable anaphref="empty" diff_type="missing" id="markable_100500115" mmax_level="target" preferred="true" sentiment_ref="empty" span="word_1628" /><markable anaphref="markable_100500115" diff_type="missing" id="markable_100500116" mmax_level="target" preferred="true" sentiment_ref="empty" span="word_1635..word_1640" /><markable anaphref="empty" diff_type="missing" id="markable_100500178" mmax_level="target" preferred="true" sentiment_ref="empty" span="word_1826..word_1828" /><markable anaphref="empty" diff_type="redundant" id="markable_100500143" mmax_level="target" preferred="true" sentiment_ref="empty" span="word_36" /><markable anaphref="empty" diff_type="redundant" id="markable_100500145" mmax_level="target" preferred="true" sentiment_ref="empty" span="word_101..word_103" /><markable anaphref="markable_100500151" diff_type="redundant" id="markable_100500152" mmax_level="target" preferred="true" sentiment_ref="empty" span="word_165..word_167" /><markable anaphref="empty" diff_type="redundant" id="markable_100500159" mmax_level="target" preferred="true" sentiment_ref="empty" span="word_345..word_346" /><markable anaphref="markable_100500184" diff_type="redundant" id="markable_100500180" mmax_level="target" preferred="true" sentiment_ref="empty" span="word_370" /><markable anaphref="empty" diff_type="redundant" id="markable_100500184" mmax_level="target" preferred="true" sentiment_ref="empty" span="word_377..word_381" /><markable anaphref="empty" diff_type="redundant" id="markable_100500167" mmax_level="target" preferred="true" sentiment_ref="empty" span="word_480" /><markable anaphref="empty" diff_type="redundant" id="markable_100500175" mmax_level="target" preferred="true" sentiment_ref="empty" span="word_532" /><markable anaphref="empty" diff_type="redundant" id="markable_100500199" mmax_level="target" preferred="true" sentiment_ref="empty" span="word_731..word_739,word_741..word_742" /><markable anaphref="empty" diff_type="redundant" id="markable_100500204" mmax_level="target" preferred="true" sentiment_ref="sentiment:markable_202" span="word_757..word_771" /><markable anaphref="empty" diff_type="redundant" id="markable_100500221" mmax_level="target" preferred="true" sentiment_ref="sentiment:markable_219" span="word_762..word_770" /><markable anaphref="empty" diff_type="redundant" id="markable_10050086" mmax_level="target" preferred="true" sentiment_ref="empty" span="word_819" /><markable anaphref="empty" diff_type="redundant" id="markable_10050087" mmax_level="target" preferred="true" sentiment_ref="empty" span="word_821..word_824" /><markable anaphref="empty" diff_type="redundant" id="markable_100500208" mmax_level="target" preferred="true" sentiment_ref="empty" span="word_839" /><markable anaphref="empty" diff_type="redundant" id="markable_100500210" mmax_level="target" preferred="true" sentiment_ref="empty" span="word_924" /><markable anaphref="empty" diff_type="redundant" id="markable_100500213" mmax_level="target" preferred="true" sentiment_ref="empty" span="word_981..word_982" /><markable anaphref="empty" diff_type="redundant" id="markable_100500108" mmax_level="target" preferred="true" sentiment_ref="empty" span="word_1050..word_1053" /><markable anaphref="empty" diff_type="redundant" id="markable_100500110" mmax_level="target" preferred="true" sentiment_ref="empty" span="word_1123..word_1126" /><markable anaphref="empty" diff_type="redundant" id="markable_100500117" mmax_level="target" preferred="true" sentiment_ref="empty" span="word_1242..word_1253" /><markable anaphref="empty" diff_type="redundant" id="markable_100500237" mmax_level="target" preferred="true" sentiment_ref="empty" span="word_1410..word_1413" /><markable anaphref="empty" diff_type="redundant" id="markable_100500239" mmax_level="target" preferred="true" sentiment_ref="empty" span="word_1486..word_1494" /><markable anaphref="empty" diff_type="redundant" id="markable_100500235" mmax_level="target" preferred="true" sentiment_ref="empty" span="word_1509" /><markable anaphref="empty" diff_type="redundant" id="markable_100500244" mmax_level="target" preferred="true" sentiment_ref="empty" span="word_1693" /><markable anaphref="empty" diff_type="redundant" id="markable_100500251" mmax_level="target" preferred="true" sentiment_ref="empty" span="word_1896" /><markable anaphref="empty" diff_type="redundant" id="markable_100500254" mmax_level="target" preferred="true" sentiment_ref="empty" span="word_1905" /><markable anaphref="empty" diff_type="redundant" id="markable_100500132" mmax_level="target" preferred="true" sentiment_ref="empty" span="word_1934..word_1936" /><markable anaphref="empty" diff_type="redundant" id="markable_100500259" mmax_level="target" preferred="true" sentiment_ref="empty" span="word_1995" /><markable anaphref="markable_100500139" diff_type="redundant" id="markable_100500140" mmax_level="target" preferred="true" sentiment_ref="empty" span="word_2037..word_2052" /><markable anaphref="empty" diff_type="redundant" id="markable_100500139" mmax_level="target" preferred="true" sentiment_ref="empty" span="word_2053" /></markables>
