<?xml version='1.0' encoding='UTF-8'?>
<!DOCTYPE markables SYSTEM "markables.dtd">
<markables xmlns="www.eml.org/NameSpaces/sentiment">
<markable id="markable_56" intensity="medium" mmax_level="sentiment" polarity="negative" sarcasm="false" span="word_929..word_937" />
<markable id="markable_4" intensity="medium" mmax_level="sentiment" polarity="negative" sarcasm="false" span="word_45..word_50" />
<markable id="markable_66" intensity="weak" mmax_level="sentiment" polarity="positive" sarcasm="false" span="word_1052..word_1070" />
<markable id="markable_79" intensity="weak" mmax_level="sentiment" polarity="negative" sarcasm="true" span="word_1223..word_1238" />
<markable id="markable_49" intensity="medium" mmax_level="sentiment" polarity="negative" sarcasm="false" span="word_809..word_823" />
<markable id="markable_14" intensity="medium" mmax_level="sentiment" polarity="negative" sarcasm="false" span="word_86..word_101" />
<markable id="markable_86" intensity="medium" mmax_level="sentiment" polarity="negative" sarcasm="false" span="word_1552..word_1562" />
<markable id="markable_75" intensity="strong" mmax_level="sentiment" polarity="positive" sarcasm="false" span="word_1188..word_1194" />
<markable id="markable_65" intensity="medium" mmax_level="sentiment" polarity="negative" sarcasm="false" span="word_1002..word_1011" />
<markable id="markable_54" intensity="weak" mmax_level="sentiment" polarity="negative" sarcasm="true" span="word_910..word_927" />
<markable id="markable_9" intensity="weak" mmax_level="sentiment" polarity="positive" sarcasm="false" span="word_79..word_84" />
<markable id="markable_72" intensity="strong" mmax_level="sentiment" polarity="positive" sarcasm="false" span="word_1181..word_1186" />
</markables>
