<?xml version='1.0' encoding='UTF-8'?>
<!DOCTYPE markables SYSTEM "markables.dtd">
<markables xmlns="www.eml.org/NameSpaces/target">
<markable anaphref="empty" diff_type="missing" id="markable_1005002" mmax_level="target" preferred="true" sentiment_ref="empty" span="word_4..word_7" /><markable anaphref="empty" diff_type="missing" id="markable_1005008" mmax_level="target" preferred="true" sentiment_ref="empty" span="word_72..word_73" /><markable anaphref="empty" diff_type="missing" id="markable_10050017" mmax_level="target" preferred="true" sentiment_ref="empty" span="word_122..word_134" /><markable anaphref="empty" diff_type="missing" id="markable_10050020" mmax_level="target" preferred="true" sentiment_ref="empty" span="word_141..word_147" /><markable anaphref="empty" diff_type="missing" id="markable_10050026" mmax_level="target" preferred="true" sentiment_ref="empty" span="word_199..word_203" /><markable anaphref="empty" diff_type="missing" id="markable_10050033" mmax_level="target" preferred="true" sentiment_ref="empty" span="word_278..word_283,word_285..word_288" /><markable anaphref="empty" diff_type="missing" id="markable_10050036" mmax_level="target" preferred="true" sentiment_ref="empty" span="word_307..word_312" /><markable anaphref="empty" diff_type="missing" id="markable_10050040" mmax_level="target" preferred="true" sentiment_ref="empty" span="word_318..word_323" /><markable anaphref="empty" diff_type="missing" id="markable_10050043" mmax_level="target" preferred="true" sentiment_ref="empty" span="word_331..word_336" /><markable anaphref="empty" diff_type="missing" id="markable_10050047" mmax_level="target" preferred="true" sentiment_ref="empty" span="word_358..word_363" /><markable anaphref="empty" diff_type="missing" id="markable_10050054" mmax_level="target" preferred="true" sentiment_ref="empty" span="word_371..word_372" /><markable anaphref="markable_10050054" diff_type="missing" id="markable_10050052" mmax_level="target" preferred="true" sentiment_ref="empty" span="word_379..word_380" /><markable anaphref="empty" diff_type="missing" id="markable_10050060" mmax_level="target" preferred="true" sentiment_ref="empty" span="word_436" /><markable anaphref="empty" diff_type="missing" id="markable_10050064" mmax_level="target" preferred="true" sentiment_ref="empty" span="word_468" /><markable anaphref="empty" diff_type="missing" id="markable_10050068" mmax_level="target" preferred="true" sentiment_ref="empty" span="word_477" /><markable anaphref="empty" diff_type="missing" id="markable_10050075" mmax_level="target" preferred="true" sentiment_ref="empty" span="word_523" /><markable anaphref="empty" diff_type="missing" id="markable_10050079" mmax_level="target" preferred="true" sentiment_ref="empty" span="word_529..word_535" /><markable anaphref="empty" diff_type="missing" id="markable_10050083" mmax_level="target" preferred="true" sentiment_ref="empty" span="word_549..word_554,word_556..word_559" /><markable anaphref="empty" diff_type="missing" id="markable_10050088" mmax_level="target" preferred="true" sentiment_ref="empty" span="word_566..word_567" /><markable anaphref="empty" diff_type="missing" id="markable_10050086" mmax_level="target" preferred="true" sentiment_ref="empty" span="word_569..word_572" /><markable anaphref="empty" diff_type="missing" id="markable_10050091" mmax_level="target" preferred="true" sentiment_ref="empty" span="word_587" /><markable anaphref="empty" diff_type="missing" id="markable_10050097" mmax_level="target" preferred="true" sentiment_ref="empty" span="word_593" /><markable anaphref="empty" diff_type="missing" id="markable_100500100" mmax_level="target" preferred="true" sentiment_ref="empty" span="word_612..word_613" /><markable anaphref="empty" diff_type="missing" id="markable_100500107" mmax_level="target" preferred="true" sentiment_ref="empty" span="word_759..word_760" /><markable anaphref="empty" diff_type="missing" id="markable_100500112" mmax_level="target" preferred="true" sentiment_ref="empty" span="word_856" /><markable anaphref="markable_100500112" diff_type="missing" id="markable_100500111" mmax_level="target" preferred="true" sentiment_ref="empty" span="word_861" /><markable anaphref="empty" diff_type="missing" id="markable_100500115" mmax_level="target" preferred="true" sentiment_ref="empty" span="word_870..word_874" /><markable anaphref="empty" diff_type="missing" id="markable_100500122" mmax_level="target" preferred="true" sentiment_ref="empty" span="word_990..word_991" /><markable anaphref="empty" diff_type="missing" id="markable_100500133" mmax_level="target" preferred="true" sentiment_ref="empty" span="word_1006..word_1010" /><markable anaphref="empty" diff_type="missing" id="markable_100500136" mmax_level="target" preferred="true" sentiment_ref="empty" span="word_1028" /><markable anaphref="empty" diff_type="missing" id="markable_100500138" mmax_level="target" preferred="true" sentiment_ref="empty" span="word_1051..word_1053" /><markable anaphref="empty" diff_type="missing" id="markable_100500144" mmax_level="target" preferred="true" sentiment_ref="empty" span="word_1107..word_1110" /><markable anaphref="empty" diff_type="missing" id="markable_100500148" mmax_level="target" preferred="true" sentiment_ref="empty" span="word_1161..word_1166" /><markable anaphref="empty" diff_type="missing" id="markable_100500153" mmax_level="target" preferred="true" sentiment_ref="empty" span="word_1186..word_1187" /><markable anaphref="empty" diff_type="missing" id="markable_100500157" mmax_level="target" preferred="true" sentiment_ref="empty" span="word_1221..word_1233" /><markable anaphref="empty" diff_type="missing" id="markable_100500159" mmax_level="target" preferred="true" sentiment_ref="empty" span="word_1235..word_1237" /><markable anaphref="empty" diff_type="missing" id="markable_100500163" mmax_level="target" preferred="true" sentiment_ref="empty" span="word_1315..word_1319" /><markable anaphref="empty" diff_type="missing" id="markable_100500167" mmax_level="target" preferred="true" sentiment_ref="empty" span="word_1351" /><markable anaphref="empty" diff_type="missing" id="markable_100500170" mmax_level="target" preferred="true" sentiment_ref="empty" span="word_1450" /><markable anaphref="empty" diff_type="missing" id="markable_100500171" mmax_level="target" preferred="true" sentiment_ref="empty" span="word_1458" /><markable anaphref="empty" diff_type="missing" id="markable_100500172" mmax_level="target" preferred="true" sentiment_ref="empty" span="word_1465" /><markable anaphref="empty" diff_type="missing" id="markable_100500175" mmax_level="target" preferred="true" sentiment_ref="empty" span="word_1479..word_1486" /><markable anaphref="empty" diff_type="missing" id="markable_100500177" mmax_level="target" preferred="true" sentiment_ref="empty" span="word_1539" /><markable anaphref="empty" diff_type="missing" id="markable_100500180" mmax_level="target" preferred="true" sentiment_ref="empty" span="word_1632" /><markable anaphref="empty" diff_type="missing" id="markable_100500183" mmax_level="target" preferred="true" sentiment_ref="empty" span="word_1649" /><markable anaphref="empty" diff_type="missing" id="markable_100500188" mmax_level="target" preferred="true" sentiment_ref="empty" span="word_1661..word_1671" /><markable anaphref="empty" diff_type="missing" id="markable_100500190" mmax_level="target" preferred="true" sentiment_ref="empty" span="word_1723..word_1724" /><markable anaphref="empty" diff_type="redundant" id="markable_10050034" mmax_level="target" preferred="true" sentiment_ref="empty" span="word_541..word_542" /><markable anaphref="empty" diff_type="redundant" id="markable_10050044" mmax_level="target" preferred="true" sentiment_ref="empty" span="word_656..word_659" /><markable anaphref="empty" diff_type="redundant" id="markable_10050047" mmax_level="target" preferred="true" sentiment_ref="empty" span="word_724..word_727" /><markable anaphref="markable_10050050" diff_type="redundant" id="markable_10050049" mmax_level="target" preferred="true" sentiment_ref="empty" span="word_903..word_907" /><markable anaphref="empty" diff_type="redundant" id="markable_10050059" mmax_level="target" preferred="false" sentiment_ref="empty" span="word_1002..word_1004" /><markable anaphref="empty" diff_type="redundant" id="markable_10050058" mmax_level="target" preferred="true" sentiment_ref="empty" span="word_1016..word_1018" /><markable anaphref="empty" diff_type="redundant" id="markable_10050062" mmax_level="target" preferred="true" sentiment_ref="empty" span="word_1095..word_1096" /></markables>
