<?xml version='1.0' encoding='UTF-8'?>
<!DOCTYPE markables SYSTEM "markables.dtd">
<markables xmlns="www.eml.org/NameSpaces/sentiment">
<markable diff_type="missing" id="10050019" intensity="medium" mmax_level="sentiment" polarity="negative" sarcasm="false" span="word_195..word_217" />
<markable diff_type="missing" id="10050024" intensity="weak" mmax_level="sentiment" polarity="negative" sarcasm="true" span="word_237..word_248" />
<markable diff_type="missing" id="10050027" intensity="medium" mmax_level="sentiment" polarity="positive" sarcasm="false" span="word_244..word_247" />
<markable diff_type="missing" id="10050033" intensity="medium" mmax_level="sentiment" polarity="positive" sarcasm="false" span="word_251..word_257" />
<markable diff_type="missing" id="10050044" intensity="medium" mmax_level="sentiment" polarity="positive" sarcasm="false" span="word_433..word_441" />
<markable diff_type="missing" id="10050055" intensity="medium" mmax_level="sentiment" polarity="positive" sarcasm="false" span="word_588..word_593,word_595..word_600" />
<markable diff_type="missing" id="10050059" intensity="medium" mmax_level="sentiment" polarity="positive" sarcasm="false" span="word_616..word_621" />
<markable diff_type="missing" id="10050065" intensity="medium" mmax_level="sentiment" polarity="positive" sarcasm="false" span="word_668..word_669" />
<markable diff_type="missing" id="10050073" intensity="medium" mmax_level="sentiment" polarity="negative" sarcasm="true" span="word_765..word_769" />
<markable diff_type="missing" id="10050074" intensity="medium" mmax_level="sentiment" polarity="negative" sarcasm="true" span="word_771..word_773" />
<markable diff_type="missing" id="10050076" intensity="medium" mmax_level="sentiment" polarity="negative" sarcasm="true" span="word_776..word_778" />
<markable diff_type="missing" id="10050075" intensity="medium" mmax_level="sentiment" polarity="positive" sarcasm="false" span="word_780..word_783" />
<markable diff_type="missing" id="10050089" intensity="strong" mmax_level="sentiment" polarity="negative" sarcasm="false" span="word_799" />
<markable diff_type="missing" id="100500101" intensity="medium" mmax_level="sentiment" polarity="positive" sarcasm="false" span="word_817..word_829" />
<markable diff_type="missing" id="100500104" intensity="medium" mmax_level="sentiment" polarity="negative" sarcasm="false" span="word_843..word_849" />
<markable diff_type="missing" id="100500108" intensity="medium" mmax_level="sentiment" polarity="positive" sarcasm="false" span="word_874..word_875" />
<markable diff_type="missing" id="100500111" intensity="medium" mmax_level="sentiment" polarity="negative" sarcasm="false" span="word_877..word_878" />
<markable diff_type="missing" id="100500119" intensity="strong" mmax_level="sentiment" polarity="negative" sarcasm="false" span="word_897..word_901" />
<markable diff_type="missing" id="100500122" intensity="medium" mmax_level="sentiment" polarity="negative" sarcasm="false" span="word_960..word_963" />
<markable diff_type="missing" id="100500126" intensity="medium" mmax_level="sentiment" polarity="negative" sarcasm="false" span="word_973..word_979" />
<markable diff_type="missing" id="100500130" intensity="medium" mmax_level="sentiment" polarity="negative" sarcasm="false" span="word_981..word_984" />
<markable diff_type="missing" id="100500134" intensity="medium" mmax_level="sentiment" polarity="negative" sarcasm="false" span="word_986..word_989" />
<markable diff_type="missing" id="100500138" intensity="medium" mmax_level="sentiment" polarity="positive" sarcasm="false" span="word_993..word_999" />
<markable diff_type="missing" id="100500142" intensity="strong" mmax_level="sentiment" polarity="positive" sarcasm="false" span="word_1001..word_1021" />
<markable diff_type="missing" id="100500156" intensity="strong" mmax_level="sentiment" polarity="negative" sarcasm="false" span="word_1047..word_1068" />
<markable diff_type="missing" id="100500165" intensity="medium" mmax_level="sentiment" polarity="negative" sarcasm="false" span="word_1109..word_1116" />
<markable diff_type="missing" id="100500170" intensity="medium" mmax_level="sentiment" polarity="negative" sarcasm="false" span="word_1227..word_1236" />
<markable diff_type="missing" id="100500174" intensity="strong" mmax_level="sentiment" polarity="negative" sarcasm="false" span="word_1239..word_1243" />
<markable diff_type="missing" id="100500181" intensity="medium" mmax_level="sentiment" polarity="positive" sarcasm="false" span="word_1355..word_1369" />
<markable diff_type="missing" id="100500188" intensity="medium" mmax_level="sentiment" polarity="negative" sarcasm="false" span="word_1392..word_1393" />
<markable diff_type="missing" id="100500191" intensity="weak" mmax_level="sentiment" polarity="negative" sarcasm="false" span="word_1397..word_1412" />
<markable diff_type="missing" id="100500193" intensity="medium" mmax_level="sentiment" polarity="negative" sarcasm="false" span="word_1421..word_1426" />
<markable diff_type="missing" id="100500197" intensity="medium" mmax_level="sentiment" polarity="positive" sarcasm="false" span="word_1520..word_1526" />
<markable diff_type="missing" id="100500203" intensity="medium" mmax_level="sentiment" polarity="negative" sarcasm="false" span="word_1570..word_1583" />
<markable diff_type="missing" id="100500207" intensity="medium" mmax_level="sentiment" polarity="negative" sarcasm="false" span="word_1693..word_1714" />
<markable diff_type="missing" id="100500211" intensity="medium" mmax_level="sentiment" polarity="negative" sarcasm="false" span="word_1769..word_1777" />
<markable diff_type="missing" id="100500216" intensity="strong" mmax_level="sentiment" polarity="negative" sarcasm="false" span="word_2074..word_2084" />
<markable diff_type="redundant" id="10050029" intensity="weak" mmax_level="sentiment" polarity="positive" sarcasm="true" span="word_414..word_425" />
<markable diff_type="redundant" id="10050047" intensity="medium" mmax_level="sentiment" polarity="negative" sarcasm="false" span="word_739..word_744" />
<markable diff_type="redundant" id="10050059" intensity="weak" mmax_level="sentiment" polarity="positive" sarcasm="false" span="word_834" />
<markable diff_type="redundant" id="10050064" intensity="weak" mmax_level="sentiment" polarity="positive" sarcasm="false" span="word_885..word_886,word_889..word_890" />
<markable diff_type="redundant" id="10050072" intensity="medium" mmax_level="sentiment" polarity="negative" sarcasm="false" span="word_1028,word_1035" />
</markables>
